qouta_manager_middleware/__init__.py
qouta_manager_middleware/constants.py
qouta_manager_middleware/validator.py
qouta_manager_middleware-0.1.0.dist-info/METADATA
qouta_manager_middleware-0.1.0.dist-info/WHEEL
qouta_manager_middleware-0.1.0.dist-info/RECORD
